GeoModeler/__init__.py
GeoModeler/_types.py
GeoModeler/feature.py
GeoModeler/featurecollection.py
GeoModeler/geometrycollection.py
GeoModeler/linestring.py
GeoModeler/multilinestring.py
GeoModeler/multipoint.py
GeoModeler/multipolygon.py
GeoModeler/point.py
GeoModeler/polygon.py
GeoModeler/utils.py
GeoModeler/validators.py
geomodeler-0.1.3b0.dist-info/METADATA
geomodeler-0.1.3b0.dist-info/WHEEL
geomodeler-0.1.3b0.dist-info/licenses/LICENSE
geomodeler-0.1.3b0.dist-info/RECORD
