Metadata-Version: 2.1
Name: GeoModeler
Version: 0.1.3b0
Summary: GeoModeler is a Python project based on pydantic, designed to model and validate geojson data structures such as points, lines, and polygons. It provides a set of tools and validators for working with GeoJSON data.
Keywords: geojson,pydantic,validation,geospatial,data-modeling
Home-page: https://github.com/jvanegmond93/geo_modeler
Author-Email: jvanegmond <jvanegmond@silverbirchgeospatial.com>
License: MIT
Classifier: Programming Language :: Python :: 3.10
Classifier: Programming Language :: Python :: 3.11
Classifier: Programming Language :: Python :: 3.12
Project-URL: Homepage, https://github.com/jvanegmond93/geo_modeler
Requires-Python: >=3.10
Requires-Dist: pydantic>=2.5.3
